django_resume/__init__.py
django_resume/admin.py
django_resume/apps.py
django_resume/entrypoints/__init__.py
django_resume/entrypoints/llm_content.py
django_resume/forms.py
django_resume/images.py
django_resume/management/commands/create_plugin_from_stdin.py
django_resume/management/commands/plugin_few_shot_context.py
django_resume/management/commands/plugin_model_from_llm_output.py
django_resume/management/commands/remove_all_resumes.py
django_resume/management/commands/remove_data_for_plugin.py
django_resume/management/commands/remove_plugin_by_name.py
django_resume/markdown.py
django_resume/migrations/0001_initial.py
django_resume/migrations/0002_alter_plugin_model.py
django_resume/migrations/__init__.py
django_resume/models.py
django_resume/plugin_generator.py
django_resume/plugins/__init__.py
django_resume/plugins/about.py
django_resume/plugins/base.py
django_resume/plugins/cover.py
django_resume/plugins/education.py
django_resume/plugins/identity.py
django_resume/plugins/permission_denied.py
django_resume/plugins/projects.py
django_resume/plugins/registry.py
django_resume/plugins/skills.py
django_resume/plugins/theme.py
django_resume/plugins/timelines.py
django_resume/plugins/tokens.py
django_resume/signals.py
django_resume/static/django_resume/css/edit.css
django_resume/static/django_resume/css/print.css
django_resume/static/django_resume/css/styles.css
django_resume/static/django_resume/fonts/inter_600.ttf
django_resume/static/django_resume/fonts/inter_600.woff2
django_resume/static/django_resume/fonts/martian_mono_200.ttf
django_resume/static/django_resume/fonts/martian_mono_200.woff2
django_resume/static/django_resume/fonts/martian_mono_300.ttf
django_resume/static/django_resume/fonts/martian_mono_300.woff2
django_resume/static/django_resume/img/jochen-illustration-footer.png
django_resume/static/django_resume/img/white-linen.png
django_resume/static/django_resume/js/edit.js
django_resume/static/django_resume/js/edit.test.js
django_resume-0.1.14.dist-info/WHEEL
django_resume-0.1.14.dist-info/entry_points.txt
django_resume-0.1.14.dist-info/METADATA
django_resume-0.1.14.dist-info/RECORD
