Metadata-Version: 2.3
Name: django-resume
Version: 0.1.14
Summary: Add your description here
Requires-Dist: django>=4.2
Requires-Python: >=3.10
Project-URL: Documentation, https://django-resume.readthedocs.io/en/latest/
Project-URL: Source, https://github.com/ephes/django-resume
